gracenote2epg/__init__.py
gracenote2epg/__main__.py
gracenote2epg/gracenote2epg_args.py
gracenote2epg/gracenote2epg_config.py
gracenote2epg/gracenote2epg_dictionaries.py
gracenote2epg/gracenote2epg_downloader.py
gracenote2epg/gracenote2epg_language.py
gracenote2epg/gracenote2epg_lineup.py
gracenote2epg/gracenote2epg_logrotate.py
gracenote2epg/gracenote2epg_parser.py
gracenote2epg/gracenote2epg_tvheadend.py
gracenote2epg/gracenote2epg_utils.py
gracenote2epg/gracenote2epg_xmltv.py
gracenote2epg/main.py
gracenote2epg/locales/gracenote2epg.pot
gracenote2epg/locales/es/LC_MESSAGES/gracenote2epg.po
gracenote2epg/locales/fr/LC_MESSAGES/gracenote2epg.po
gracenote2epg-1.6.0.data/data/bin/tv_grab_gracenote2epg
gracenote2epg-1.6.0.data/data/share/doc/gracenote2epg/LICENSE
gracenote2epg-1.6.0.data/data/share/doc/gracenote2epg/cache-retention.md
gracenote2epg-1.6.0.data/data/share/doc/gracenote2epg/changelog.md
gracenote2epg-1.6.0.data/data/share/doc/gracenote2epg/configuration.md
gracenote2epg-1.6.0.data/data/share/doc/gracenote2epg/development.md
gracenote2epg-1.6.0.data/data/share/doc/gracenote2epg/installation.md
gracenote2epg-1.6.0.data/data/share/doc/gracenote2epg/lineup-configuration.md
gracenote2epg-1.6.0.data/data/share/doc/gracenote2epg/log-rotation.md
gracenote2epg-1.6.0.data/data/share/doc/gracenote2epg/troubleshooting.md
gracenote2epg-1.6.0.data/data/share/doc/gracenote2epg/tvheadend.md
gracenote2epg-1.6.0.data/data/share/gracenote2epg/gracenote2epg.xml
gracenote2epg-1.6.0.data/scripts/tv_grab_gracenote2epg
gracenote2epg-1.6.0.dist-info/LICENSE
gracenote2epg-1.6.0.dist-info/METADATA
gracenote2epg-1.6.0.dist-info/WHEEL
gracenote2epg-1.6.0.dist-info/entry_points.txt
gracenote2epg-1.6.0.dist-info/top_level.txt
gracenote2epg-1.6.0.dist-info/RECORD
