Metadata-Version: 2.1
Name: gracenote2epg
Version: 1.6.0
Summary: TV Guide Grabber for North America
Home-page: https://github.com/th0ma7/gracenote2epg
Author: th0ma7
Author-email: th0ma7@gmail.com
License: GPL-3.0
Project-URL: Bug Reports, https://github.com/th0ma7/gracenote2epg/issues
Project-URL: Source, https://github.com/th0ma7/gracenote2epg
Project-URL: Documentation, https://github.com/th0ma7/gracenote2epg/tree/main/docs
Project-URL: TVheadend Guide, https://github.com/th0ma7/gracenote2epg/blob/main/docs/tvheadend.md
Keywords: xmltv epg tv guide gracenote tvheadend ota cable geocoding
Classifier: Development Status :: 5 - Production/Stable
Classifier: Intended Audience :: End Users/Desktop
Classifier: Topic :: Multimedia :: Video
Classifier: License :: OSI Approved :: GNU General Public License v3 (GPLv3)
Classifier: Programming Language :: Python :: 3
Classifier: Programming Language :: Python :: 3.7
Classifier: Programming Language :: Python :: 3.8
Classifier: Programming Language :: Python :: 3.9
Classifier: Programming Language :: Python :: 3.10
Classifier: Programming Language :: Python :: 3.11
Classifier: Operating System :: OS Independent
Classifier: Environment :: Console
Requires-Python: >=3.7
License-File: LICENSE
Requires-Dist: requests >=2.25.0
Provides-Extra: dev
Requires-Dist: langdetect >=1.0.9 ; extra == 'dev'
Requires-Dist: polib >=1.1.0 ; extra == 'dev'
Requires-Dist: pgeocode >=0.4.0 ; extra == 'dev'
Requires-Dist: pytest >=6.0 ; extra == 'dev'
Requires-Dist: flake8 >=3.8 ; extra == 'dev'
Requires-Dist: black >=21.0 ; extra == 'dev'
Requires-Dist: mypy >=0.910 ; extra == 'dev'
Requires-Dist: autoflake >=1.4 ; extra == 'dev'
Requires-Dist: build >=0.7.0 ; extra == 'dev'
Requires-Dist: twine >=3.4.0 ; extra == 'dev'
Provides-Extra: full
Requires-Dist: langdetect >=1.0.9 ; extra == 'full'
Requires-Dist: polib >=1.1.0 ; extra == 'full'
Requires-Dist: pgeocode >=0.4.0 ; extra == 'full'
Provides-Extra: geocoding
Requires-Dist: pgeocode >=0.4.0 ; extra == 'geocoding'
Provides-Extra: langdetect
Requires-Dist: langdetect >=1.0.9 ; extra == 'langdetect'
Provides-Extra: test
Requires-Dist: pytest >=6.0 ; extra == 'test'
Requires-Dist: pytest-cov >=2.10 ; extra == 'test'
Provides-Extra: translations
Requires-Dist: polib >=1.1.0 ; extra == 'translations'
